wattrex_cycler_db_sync/__init__.py
wattrex_cycler_db_sync/__version__.py
wattrex_cycler_db_sync/context.py
wattrex_cycler_db_sync/db_sync_fachade.py
wattrex_cycler_db_sync/db_sync_node.py
wattrex_cycler_db_sync-1.0.3.dist-info/LICENSE.txt
wattrex_cycler_db_sync-1.0.3.dist-info/METADATA
wattrex_cycler_db_sync-1.0.3.dist-info/WHEEL
wattrex_cycler_db_sync-1.0.3.dist-info/top_level.txt
wattrex_cycler_db_sync-1.0.3.dist-info/RECORD
